datastore/__init__.py
datastore/client.py
datastore/schema.py
datastore/utils.py
datastore/connectors/__init__.py
datastore/connectors/base.py
datastore/connectors/cassandra.py
datastore/connectors/http.py
datastore/connectors/kafka.py
datastore/connectors/minio.py
datastore/connectors/postgres.py
datastore/connectors/redis.py
os_datastore-1.0.0.dist-info/LICENSE
os_datastore-1.0.0.dist-info/METADATA
os_datastore-1.0.0.dist-info/WHEEL
os_datastore-1.0.0.dist-info/top_level.txt
os_datastore-1.0.0.dist-info/RECORD
