Metadata-Version: 2.1
Name: os-datastore
Version: 1.0.0
Summary: A datastore SDK for accessing various data sources via URN
Home-page: https://github.com/yourusername/datastore
Author: uloveits
Author-email: Your Name <your.email@example.com>
License: MIT
Keywords: datastore,sdk,urn,database,storage
Classifier: Development Status :: 4 - Beta
Classifier: Intended Audience :: Developers
Classifier: Topic :: Software Development :: Libraries :: Python Modules
Classifier: License :: OSI Approved :: MIT License
Classifier: Programming Language :: Python :: 3
Classifier: Programming Language :: Python :: 3.7
Classifier: Programming Language :: Python :: 3.8
Classifier: Programming Language :: Python :: 3.9
Classifier: Programming Language :: Python :: 3.10
Classifier: Programming Language :: Python :: 3.11
Requires-Python: >=3.7
License-File: LICENSE
Requires-Dist: requests>=2.28.0
Requires-Dist: jsonschema>=4.17.0
Requires-Dist: minio>=7.1.0
Requires-Dist: cassandra-driver>=3.27.0
Requires-Dist: redis>=4.5.0
Requires-Dist: kafka-python>=2.0.2
Requires-Dist: urllib3>=1.26.0
Provides-Extra: dev
Requires-Dist: pytest>=7.0.0; extra == "dev"
Requires-Dist: pytest-cov>=4.0.0; extra == "dev"
Requires-Dist: black>=23.0.0; extra == "dev"
Requires-Dist: flake8>=6.0.0; extra == "dev"
